nettraffic/__init__.py
nettraffic-0.0.2.dist-info/DESCRIPTION.rst
nettraffic-0.0.2.dist-info/METADATA
nettraffic-0.0.2.dist-info/metadata.json
nettraffic-0.0.2.dist-info/RECORD
nettraffic-0.0.2.dist-info/top_level.txt
nettraffic-0.0.2.dist-info/WHEEL
